magic_sdk/__init__.py
magic_sdk-0.0.1.dist-info/LICENSE.txt
magic_sdk-0.0.1.dist-info/METADATA
magic_sdk-0.0.1.dist-info/WHEEL
magic_sdk-0.0.1.dist-info/top_level.txt
magic_sdk-0.0.1.dist-info/RECORD
